src/pdf2remarkable.py
src/utils.py
pdf2remarkable-0.1.0.dist-info/LICENSE
pdf2remarkable-0.1.0.dist-info/METADATA
pdf2remarkable-0.1.0.dist-info/WHEEL
pdf2remarkable-0.1.0.dist-info/entry_points.txt
pdf2remarkable-0.1.0.dist-info/RECORD
