Metadata-Version: 2.3
Name: pdf2remarkable
Version: 0.1.0
Summary: 
Author: Robert Dargavel Smith
Author-email: teticio@gmail.com
Requires-Python: >=3.10,<4.0
Classifier: Programming Language :: Python :: 3
Classifier: Programming Language :: Python :: 3.10
Classifier: Programming Language :: Python :: 3.11
Classifier: Programming Language :: Python :: 3.12
Classifier: Programming Language :: Python :: 3.13
Requires-Dist: pypdf (>=5.0.1,<6.0.0)
Requires-Dist: requests (>=2.31.0,<3.0.0)
